slack_async_alert/__init__.py
slack_async_alert/configure.py
slack_async_alert/constant.py
slack_async_alert/run.py
slack_async_alert/slack.py
slack_async_alert/slrt
slack_async_alert-1.0.3.dist-info/METADATA
slack_async_alert-1.0.3.dist-info/WHEEL
slack_async_alert-1.0.3.dist-info/entry_points.txt
slack_async_alert-1.0.3.dist-info/top_level.txt
slack_async_alert-1.0.3.dist-info/RECORD
